Metadata-Version: 2.1
Name: templaty
Version: 1.3.2
Summary: Generate programming code from template files
Home-page: https://github.com/samvv/Templaty
Author: Sam Vervaeck
Author-email: vervaeck.sam@skynet.be
License: UNKNOWN
Project-URL: Bug Reports, https://github.com/samvv/Templaty/issues
Project-URL: Source, https://github.com/samvv/Templaty/
Keywords: template code-generator c++ c php java python
Platform: UNKNOWN
Classifier: Development Status :: 5 - Production/Stable
Classifier: Intended Audience :: Developers
Classifier: Topic :: Software Development :: Code Generators
Classifier: License :: OSI Approved :: MIT License
Classifier: Programming Language :: Python :: 3.5
Classifier: Programming Language :: Python :: 3.6
Classifier: Programming Language :: Python :: 3.7
Requires-Python: >=3.5, <4
Provides-Extra: dev
Provides-Extra: test
